atomlib/__init__.py
atomlib/__main__.py
atomlib/atomcell.py
atomlib/atoms.py
atomlib/bbox.py
atomlib/cell.py
atomlib/cli.py
atomlib/disloc.py
atomlib/elem.py
atomlib/expr.py
atomlib/mixins.py
atomlib/transform.py
atomlib/types.py
atomlib/util.py
atomlib/vec.py
atomlib/data/ion_radii.json
atomlib/data/masses.npy
atomlib/data/radii.npy
atomlib/data/template.mslice
atomlib/io/__init__.py
atomlib/io/cfg.py
atomlib/io/cif.py
atomlib/io/lmp.py
atomlib/io/mp_api.py
atomlib/io/mslice.py
atomlib/io/qe.py
atomlib/io/xsf.py
atomlib/io/xyz.py
atomlib/make/__init__.py
atomlib/testing/__init__.py
atomlib/visualize/__init__.py
atomlib-0.3.dist-info/LICENSE.txt
atomlib-0.3.dist-info/METADATA
atomlib-0.3.dist-info/WHEEL
atomlib-0.3.dist-info/entry_points.txt
atomlib-0.3.dist-info/top_level.txt
atomlib-0.3.dist-info/RECORD
