Metadata-Version: 2.1
Name: atomlib
Version: 0.3
Summary: A collection of utilities to manipulate atomic structures
Author-email: Colin Gilgenbach <hexane@mit.edu>
License: Mozilla Public License Version 2.0
Project-URL: Repository, https://github.com/hexane360/atomlib.git
Project-URL: Documentation, https://hexane360.github.io/atomlib/
Keywords: science,atoms,materials,chemistry
Classifier: Programming Language :: Python :: 3
Classifier: Programming Language :: Python :: 3 :: Only
Classifier: Programming Language :: Python :: 3.9
Classifier: Programming Language :: Python :: 3.10
Classifier: Programming Language :: Python :: 3.11
Classifier: Programming Language :: Python :: 3.12
Classifier: Development Status :: 4 - Beta
Classifier: Intended Audience :: Science/Research
Classifier: Topic :: Scientific/Engineering :: Physics
Classifier: License :: OSI Approved :: Mozilla Public License 2.0 (MPL 2.0)
Classifier: Typing :: Typed
Requires-Python: >=3.9
License-File: LICENSE.txt
Requires-Dist: click (~=8.1)
Requires-Dist: numpy (~=1.22)
Requires-Dist: scipy (~=1.8)
Requires-Dist: polars (~=0.17.5)
Requires-Dist: matplotlib (~=3.5)
Requires-Dist: requests (~=2.28)
Requires-Dist: importlib-resources (>=5.0)
Requires-Dist: typing-extensions (~=4.4) ; python_version < "3.10"
Provides-Extra: dev
Requires-Dist: pytest (>=6.2.4) ; extra == 'dev'
Requires-Dist: pytest-cov (>=3.0.0) ; extra == 'dev'
Requires-Dist: coveragepy-lcov (>=0.1.1) ; extra == 'dev'
Requires-Dist: nbmake (>=1.4.1) ; extra == 'dev'
Provides-Extra: docs
Requires-Dist: sphinx (~=6.0) ; extra == 'docs'
Requires-Dist: sphinx-rtd-theme (~=1.0) ; extra == 'docs'
